1_BasicVerilog/00_halfAdder.v
module half_adder (
    x,y,s,c
);
    input x,y;
    output s,c;
    xor(s,x,y);
    and(c,x,y);
endmodule

1_BasicVerilog/01_fullAdder.v
module full_adder (
    x,y,z,s,c
);
    input x,y,z;
    output s,c;
    wire hs,hc,tc;
    half_adder ha1(x,y,hs,hc);
    half_adder ha2(hs,z,s,tc);
    or(c,tc,hc);
endmodule

1_BasicVerilog/01_fullAdder_tb.v
module full_adder_tb;
// iverilog -o 01_fullAdder.vvp .\01_fullAdder_tb.v .\01_fullAdder.v .\00_halfAdder.v
// vvp .\01_fullAdder.vvp
    reg x,y,z;
    wire s,c;

    initial begin
        $dumpfile("01_fullAdder.vcd");
        $dumpvars(0,f);
        $monitor("x = %b, y = %b, z=%b | s = %b, c = %b ", x, y, z, s, c);
        #50 x=1'b0; y=1'b0; z=1'b0;
        #50 x=1'b0; y=1'b0; z=1'b1;
        #50 x=1'b0; y=1'b1; z=1'b0;
        #50 x=1'b0; y=1'b1; z=1'b1;
        #50 x=1'b1; y=1'b0; z=1'b0;
        #50 x=1'b1; y=1'b0; z=1'b1;
        #50 x=1'b1; y=1'b1; z=1'b0;
        #50 x=1'b1; y=1'b1; z=1'b1;
        #50 $finish;
    end

    full_adder f(x,y,z,s,c);
endmodule

01_fullAdder.vcd
$date
	Fri Mar 05 06:39:18 2021
$end
$version
	Icarus Verilog
$end
$timescale
	1s
$end
$scope module full_adder_tb $end
$scope module f $end
$var wire 1 ! c $end
$var wire 1 " x $end
$var wire 1 # y $end
$var wire 1 $ z $end
$var wire 1 % tc $end
$var wire 1 & s $end
$var wire 1 ' hs $end
$var wire 1 ( hc $end
$scope module ha1 $end
$var wire 1 ( c $end
$var wire 1 ' s $end
$var wire 1 " x $end
$var wire 1 # y $end
$upscope $end
$scope module ha2 $end
$var wire 1 % c $end
$var wire 1 & s $end
$var wire 1 ' x $end
$var wire 1 $ y $end
$upscope $end
$upscope $end
$upscope $end
$enddefinitions $end
#0
$dumpvars
x(
x'
x&
x%
x$
x#
x"
x!
$end
#50
0!
0&
0%
0'
0(
0$
0#
0"
#100
1&
1$
#150
1'
0$
1#
#200
1!
0&
1%
1$
#250
0!
1&
0%
0$
0#
1"
#300
1!
0&
1%
1$
#350
0%
0'
1(
0$
1#
#400
1&
1$
