1_protocal_study/7.i2c_zswang/i2c_slave.v
/*
 * I2C interface slave module.
 * 2021/07/27 start writing this program, 
 *
 * yeah, master is too hard for me at this moment.😂
 * basic function:
 * 1. receive START, STOP.
 * 2. receive 7-bit address, compare address, and ACK.
 *
 * Copyright (C) 2021 Shawn ZS Wang <ZS_Wang@wistron.com>
 * Distributed under the terms of GPLv2 or (at your option) any later version.
 */
module i2c_slave (
    SDA,
    SCL,
);

inout SDA;
input SCL;

reg sda_en = 0, sda_data = 0;
assign SDA = (sda_en) ? sda_data : 1'bz;

//---------------------------------------------
// Pararmeter Declaration
//---------------------------------------------
parameter I2C_ADDR = 7'h27;

//---------------------------------------------
// State Declaration
//---------------------------------------------
parameter IDLE = 8;
parameter ADDR7 = 7;
parameter ADDR6 = 6;
parameter ADDR5 = 5;
parameter ADDR4 = 4;
parameter ADDR3 = 3;
parameter ADDR2 = 2;
parameter ADDR1 = 1;
parameter RW = 0;

//---------------------------------------------
// start,stop condition
//---------------------------------------------
reg start = 0, stop = 0;
always @ ( negedge SDA )
    if(SCL) begin
        start = 1;
        stop = 0;
    end
always @ ( posedge SDA )
    if(SCL) begin
        stop = 1;
        start = 0;
    end
//---------------------------------------------
// State counter
//---------------------------------------------
reg [3:0] state = IDLE;
always @(negedge SCL) begin
    // loop state while start
    if(start && state > RW)
        state = state - 1;
    if(stop)
        state = IDLE;
    // check ACK, take SDA
    if( ack==1 && state==RW) begin
        sda_en = 1;
        sda_data = 0;
        state = IDLE;
    end
    // back to IDLE state, return SDA
    else begin
        ack = 0;
        sda_data = 0;
        sda_en = 0;
    end

end

//---------------------------------------------
// Address matching & Send ACK
//---------------------------------------------
reg [6:0] addr_diff = 7'd0;
reg ack = 0, nack = 0;
reg rw = 0;
always @(posedge SCL) begin
    // Address check difference
    if( state<IDLE & ack==0 & state>RW ) begin 
        addr_diff[state-1] = I2C_ADDR[state-1] ^ SDA; //check I2C_ADDR[6:0]
    end 
    // Calculate if ACK
    if( ~(|addr_diff[6:0]) && state==RW ) begin
        ack = 1;
        rw = SDA;
    end
end

endmodule

//---------------------------------------------
// TESTBENCH
//---------------------------------------------
`timescale 1s/1ms
module tb;
    reg scl;
    wire sda;
    reg sda_en = 0, sda_data = 0;
    assign sda = (sda_en) ? sda_data : 1'bz;

    i2c_slave i2cs0(
        .SDA (sda),
        .SCL (scl)
    );

    task tick;
    begin
        scl = ~scl;
    end
    endtask

    task tick2;
    begin
        scl = 0; 
        #1 ;
        scl = 1; 
        #1 ;
    end
    endtask

    initial begin
        $dumpfile("i2c_slave.vcd");
        $dumpvars();
        scl=1;
        sda_en=1;
        sda_data=1;
    end

    initial #30 $finish;

    // Sim master signal
    initial begin

        #1 ; // Better looking of waveform
        sda_data = 0; // START 
        #1 ; // delay #1 to start transmission
        sda_data = 0; tick2; // ADDR 7 (set value at low SCL, and gen a whole SCL cycle)
        sda_data = 1; tick2; // ADDR 6
        sda_data = 0; tick2; // ADDR 5
        sda_data = 0; tick2; // ADDR 4
        sda_data = 1; tick2; // ADDR 3
        sda_data = 1; tick2; // ADDR 2
        sda_data = 1; tick2; // ADDR 1
        sda_data = 1; tick2; // READ
        sda_en = 0; sda_data = 0; tick2; // hand over control of SDA, wait ACK
        sda_en = 1; tick2; // take back control of SDA
        #0.5 sda_data = 0; #0.5 sda_data = 1; // STOP
    end
endmodule

2_Protocal_tb/7.i2c_zswang/i2c_slave.vcd
$date
	Mon Aug 02 10:47:55 2021
$end
$version
	Icarus Verilog
$end
$timescale
	1ms
$end
$scope module tb $end
$var wire 1 ! sda $end
$var reg 1 " scl $end
$var reg 1 # sda_data $end
$var reg 1 $ sda_en $end
$scope module i2cs0 $end
$var wire 1 " SCL $end
$var wire 1 ! SDA $end
$var reg 1 % ack $end
$var reg 7 & addr_diff [6:0] $end
$var reg 1 ' nack $end
$var reg 1 ( rw $end
$var reg 1 ) sda_data $end
$var reg 1 * sda_en $end
$var reg 1 + start $end
$var reg 4 , state [3:0] $end
$var reg 1 - stop $end
$upscope $end
$scope task tick $end
$upscope $end
$scope task tick2 $end
$upscope $end
$upscope $end
$enddefinitions $end
#0
$dumpvars
1-
b1000 ,
0+
0*
0)
0(
0'
b0 &
0%
1$
1#
1"
1!
$end
#1000
0-
1+
0!
0#
#2000
b111 ,
0"
#3000
1"
#4000
b110 ,
1!
0"
1#
#5000
1"
#6000
b101 ,
0!
0"
0#
#7000
1"
#8000
b100 ,
0"
#9000
1"
#10000
b11 ,
1!
0"
1#
#11000
1"
#12000
b10 ,
0"
#13000
1"
#14000
b1 ,
0"
#15000
1"
#16000
b0 ,
0"
#17000
1(
1%
1"
#18000
b1000 ,
1*
0!
0"
0#
0$
#19000
1"
#20000
0*
0%
b111 ,
0"
1$
#21000
1"
#23000
0+
1-
1!
1#
