1_protocal_study/3.lpc/lpc.v
/*
 * LPC interface module.
 *
 * Hardwired to 0x03fx address range (see inline comments), implementing just
 * the few bits in the status register and the data I/O.
 *
 * Sufficient for the Coreboot console and the SerialICE input.
 *
 * Copyright (C) 2017 Lubomir Rintel <lkundrak@v3.sk>
 * Distributed under the terms of GPLv2 or (at your option) any later version.
 */

module lpc (
	lpc_clk,
	lpc_rst,
	lpc_data,
	lpc_frame,
	tx_data,
	tx_data_valid,
	rx_data,
	rx_data_valid,
	tx_busy
);
	reg rd = 0;
	reg lpc_data_out = 0;
	reg [3:0] out_data = 4'hf;

	input lpc_clk;
	input lpc_rst;

	inout [3:0] lpc_data;
	input lpc_frame;

	output [7:0] tx_data;
	output tx_data_valid;

	input [7:0] rx_data;
	input rx_data_valid;

	input tx_busy;

	wire lpc_clk;
	wire lpc_rst;
	wire tx_busy;
	assign lpc_data = lpc_data_out ? out_data : 4'bZ;
	wire lpc_frame;

	reg [7:0] tx_data = 0;
	reg tx_data_valid = 1'bz;

	parameter START = 0;
	parameter CTDIR = 1;
	parameter ADDR0 = 2;
	parameter ADDR1 = 3;
	parameter ADDR2 = 4;
	parameter ADDR3 = 5;
	parameter WDATA0 = 6;
	parameter WDATA1 = 7;
	parameter TAR0 = 8;
	parameter SYNC = 9;
	parameter RDATA0 = 10;
	parameter RDATA1 = 11;
	parameter TAR1 = 12;
	reg [3:0] state = START;

	reg status_port = 0;

	reg [7:0] rxbuf[3:0];
	reg [1:0] rx_begin = 0;
	reg [1:0] rx_end = 0;

	always @(posedge lpc_clk)
	begin


		if (rx_data_valid)
		begin
			$display("LPC RX: [%x]", rx_data);
			rxbuf[rx_end] <= rx_data;
			rx_end <= rx_end + 1;
		end

//		$display("RXBUF: begin=%d end=%d [%02x,%02x,%02x,%02x,%02x,%02x,%02x,%02x]", rx_begin, rx_end,
//			rxbuf[0], rxbuf[1], rxbuf[2], rxbuf[3], rxbuf[4], rxbuf[5], rxbuf[6], rxbuf[7]);

		//$display("LPCCLK: [%d] [%x] [%x]", state, lpc_frame, lpc_data);
		if (lpc_frame == 0)
		begin
			if (lpc_data == 0)
				state <= CTDIR;
			else
				state <= START;
		end
		else
		begin
			case (state)
			START:
				tx_data_valid <= 0;
			CTDIR:
				if (lpc_data == 0)
				begin
					rd <= 1;
					state <= ADDR0;
				end
				else if (lpc_data == 2)
				begin
					rd <= 0;
					state <= ADDR0;
				end
				else
					state <= START;
			ADDR0:
				// 0x03fx
				//   ^ the most significant address nibble
				if (lpc_data == 0)
					state <= ADDR1;
				else
					state <= START;
			ADDR1:
				// 0x03fx
				//    ^ second address nibble
				if (lpc_data == 'h3)
					state <= ADDR2;
				else
					state <= START;
			ADDR2:
				// 0x03fx
				//     ^ third address nibble
				if (lpc_data == 'hf)
					state <= ADDR3;
				else
					state <= START;
			ADDR3:
			begin
				// 0x03fx
				//      ^ d || 8
				if (lpc_data[3:0] == 4'hd || lpc_data[3:0] == 4'h8)
				begin
					status_port <= lpc_data[0];
					if (rd == 1)
						state <= TAR0;
					else
						state <= WDATA0;
				end
				else
					state <= START;
			end
			WDATA0:
			begin
				tx_data[3:0] <= lpc_data;
				state <= WDATA1;
			end
			WDATA1:
			begin
				tx_data[7:4] <= lpc_data;
				state <= TAR0;
			end
			TAR0:
			begin
				lpc_data_out <= 1;
				state <= SYNC;
			end
			SYNC:
			begin
				out_data <= 0;
				if (rd)
					state <= RDATA0;
				else
				begin
					tx_data_valid <= 1;
					state <= TAR1;
				end
			end
			RDATA0:
			begin
				if (status_port)
					out_data <= rx_begin != rx_end;
				else if (rx_begin != rx_end)
					out_data <= rxbuf[rx_begin][3:0];
				else
					out_data <= 4'hf;
				state <= RDATA1;
			end
			RDATA1:
			begin
				if (status_port)
					out_data <= (tx_busy ? 0 : 6);
				else if (rx_begin != rx_end)
				begin
					out_data <= rxbuf[rx_begin][7:4];
					rx_begin <= rx_begin + 1;
				end
				else
					out_data <= 4'hf;
				state <= TAR1;
			end
			TAR1:
			begin
				lpc_data_out <= 0;
				state <= START;
			end
			endcase
		end
	end
endmodule

1_protocal_study/3.lpc/lpc_tb.v
`include "lpc.v"
`default_nettype none

module tb_lpc;
reg clk = 0;
reg rst_n;

reg sel = 1;
reg [3:0] data = 4'hf;
inout [3:0] lpc_data;
assign lpc_data = sel ? data : 4'bZ;

reg lpc_frame = 1;
wire [7:0] tx_data;
wire tx_data_valid;
reg [7:0] rx_data;
reg rx_data_valid;
reg tx_busy = 0;

reg [7:0] read_data;

lpc lpc0
(
	.lpc_clk(clk),
	.lpc_rst(rst_n),
	.lpc_data(lpc_data),
	.lpc_frame(lpc_frame),
	.tx_data(tx_data),
	.tx_data_valid(tx_data_valid),
	.rx_data(rx_data),
	.rx_data_valid(rx_data_valid),
	.tx_busy(tx_busy)
);



initial begin
    $dumpfile("lpc_tb.vcd");
    $dumpvars(0, tb_lpc);
end

task tick;
    begin
	# 1 clk = 1;
	# 1 clk = 0;
    end
endtask

task lpc_write;
    begin
    sel = 1;
    lpc_frame<=0;
    data<=0;
    tick;
    lpc_frame<=1;
    data<=2;
    tick;
    data<=4'h0;
    tick;
    data<=4'h3;
    tick;
    data<=4'hf;
    tick;
    data<=4'hd;
    tick;
    data<=4'hB;
    tick;
    data<=4'hA;
    tick;
    sel = 0;
    end
endtask

task lpc_read;
input [15:0] port;
output [7:0] read_value;
begin
    sel <= 1;
    // START
    lpc_frame<=0;
    data<=0;
    tick;
    // CTDIR
    lpc_frame<=1;
    data<=0;
    tick;
    // ADDR0
    data<=port[15:12];
    tick;
    // ADDR1
    data<=port[11:8];
    tick;
    // ADDR2
    data<=port[7:4];
    tick;
    // ADDR3
    data<=port[3:0];
    tick;
    // TAR0
    sel <= 0;
	tick;
	// SYNC
	tick;
    // DATA0
    tick;
    read_value[3:0] <= lpc_data;
    // DATA1
    tick;
    read_value[7:4] <= lpc_data;
    sel <= 1;
    // TAR1
    tick;
end    
endtask

initial begin
    rst_n<=1;
    tick;
    rst_n<=0;
    tick;
    rst_n<=1;
    lpc_read (16'h3fd, read_data);
    repeat(2) tick;
    
    $finish(2);
end

endmodule
`default_nettype wire

2_Protocal_tb/3.lpc/lpc_tb.vcd
$date
	Tue Jul 13 17:24:10 2021
$end
$version
	Icarus Verilog
$end
$timescale
	1s
$end
$scope module tb_lpc $end
$var wire 4 ! lpc_data [3:0] $end
$var wire 1 " tx_data_valid $end
$var wire 8 # tx_data [7:0] $end
$var reg 1 $ clk $end
$var reg 4 % data [3:0] $end
$var reg 1 & lpc_frame $end
$var reg 8 ' read_data [7:0] $end
$var reg 1 ( rst_n $end
$var reg 8 ) rx_data [7:0] $end
$var reg 1 * rx_data_valid $end
$var reg 1 + sel $end
$var reg 1 , tx_busy $end
$scope module lpc0 $end
$var wire 1 $ lpc_clk $end
$var wire 4 - lpc_data [3:0] $end
$var wire 1 & lpc_frame $end
$var wire 1 ( lpc_rst $end
$var wire 8 . rx_data [7:0] $end
$var wire 1 * rx_data_valid $end
$var wire 1 , tx_busy $end
$var reg 1 / lpc_data_out $end
$var reg 4 0 out_data [3:0] $end
$var reg 1 1 rd $end
$var reg 2 2 rx_begin [1:0] $end
$var reg 2 3 rx_end [1:0] $end
$var reg 4 4 state [3:0] $end
$var reg 1 5 status_port $end
$var reg 8 6 tx_data [7:0] $end
$var reg 1 " tx_data_valid $end
$upscope $end
$scope task lpc_read $end
$var reg 16 7 port [15:0] $end
$var reg 8 8 read_value [7:0] $end
$upscope $end
$scope task lpc_write $end
$upscope $end
$scope task tick $end
$upscope $end
$upscope $end
$enddefinitions $end
#0
$dumpvars
bx 8
bx 7
b0 6
05
b0 4
b0 3
b0 2
01
b1111 0
0/
bx .
b1111 -
0,
1+
x*
bx )
1(
bx '
1&
b1111 %
0$
b0 #
z"
b1111 !
$end
#1
0"
1$
#2
0(
0$
#3
1$
#4
b0 !
b0 -
b0 %
0&
1(
b1111111101 7
0$
#5
b1 4
1$
#6
1&
0$
#7
b10 4
11
1$
#8
0$
#9
b11 4
1$
#10
b11 !
b11 -
b11 %
0$
#11
b100 4
1$
#12
b1111 !
b1111 -
b1111 %
0$
#13
b101 4
1$
#14
b1101 !
b1101 -
b1101 %
0$
#15
b1000 4
15
1$
#16
bz !
bz -
0+
0$
#17
b1111 !
b1111 -
b1001 4
1/
1$
#18
0$
#19
b0 !
b0 -
b1010 4
b0 0
1$
#20
0$
#21
b1011 4
1$
#22
bx0000 8
0$
#23
b110 !
b110 -
b1100 4
b110 0
1$
#24
bx1xx !
bx1xx -
1+
b1100000 8
0$
#25
b1101 !
b1101 -
b0 4
0/
1$
#26
b1100000 '
0$
