1_protocal_study/6.i2c_csdn/i2c_csdn.v

`timescale 1ns / 1ps
module I2CTEST(
SDA, SCL
);
 
input SCL;
inout SDA;
 
// The 7-bits address that we want for our I2C slave
parameter I2C_ADR = 7'h13;
 
//---------------------------------------------
//start,stop condition judgement
//---------------------------------------------
wire start, stop;
reg sda1, sda2;
reg sda11;
 
always @ ( posedge SCL )
sda1 <= SDA;
always @ ( negedge SCL )
sda2 <= SDA;
always @ ( negedge SCL )
sda11 <= sda1;
assign start = sda11 & (!sda2);
assign stop = sda2 & ( !sda11 );
//----------------------------------------------
//count setting
//----------------------------------------------
reg [3:0]  bitcont;
wire bit_ack = bitcont[3];
always @ ( posedge SCL or posedge start)
begin
    if ( start )
    bitcont <=  4'h6;
    else
    begin
        if (bit_ack)
        bitcont <= 4'h6;
        else
        bitcont <= bitcont -4'h1;
    end
end
//-------------------------------------
//get sda using posedge scl
//-------------------------------------
reg sdar;
always @ ( posedge SCL ) sdar <= SDA;
//----------------------------------------
//address match
//----------------------------------------
reg addr_match, op_read;
always @ ( negedge SCL or posedge start )
begin
    if ( start )
    begin
        addr_match <= 1'h1;
        op_read <= 1'h0;
    end
    else
    begin
        if( (bitcont == 6) & (sdar != I2C_ADR[6])) addr_match <= 1'h0;
        if( (bitcont == 5) & (sdar != I2C_ADR[5])) addr_match <= 1'h0;
        if( (bitcont == 4) & (sdar != I2C_ADR[4])) addr_match <= 1'h0;
        if( (bitcont == 3) & (sdar != I2C_ADR[3])) addr_match <= 1'h0;
        if( (bitcont == 2) & (sdar != I2C_ADR[2])) addr_match <= 1'h0;
        if( (bitcont == 1) & (sdar != I2C_ADR[1])) addr_match <= 1'h0;
        if( (bitcont == 0) & (sdar != I2C_ADR[0])) addr_match <= 1'h0;
        if( bitcont == 0 ) op_read <= sdar;
    end
end
//-----------------------------------------------------------------------
//send ack
//-----------------------------------------------------------------------
reg ack_assert;
always @ ( negedge SCL )
begin
    if ( bit_ack & addr_match & op_read )
    ack_assert <= 1'h1;
    else
    ack_assert <= 1'h0;
end
//-------------------------------------------------------------------------
//control SDA line
//-------------------------------------------------------------------------
assign SDA = ack_assert ? 1'h0 : 1'hz;
pullup ( SDA );
endmodule

2_Protocal_tb/6.i2c_csdn/i2c_csdn_tb.v
`include "i2c_csdn.v"
`timescale 1ns / 1ps
module test(
sda
);
 
	reg	scl;
	inout sda;
	reg	sda_out;
	wire	sda_in;
	reg	[7:0]	data;
	
	reg start_flag, stop_flag;
	
	assign sda = sda_out ? 1'bz : 1'b0;
	assign sda_in = sda;
	pullup( sda );
	
	
	I2CTEST testmine(.SDA(sda), .SCL(scl));
 
    initial begin
        $dumpfile("i2c_csdn_tb.vcd");
        $dumpvars();
    end

    initial begin
        #100000 $finish;
    end

	initial
		begin
		   scl = 0;
			sda_out = 0;
			data = 8'h27;
			start_flag = 0;
			#160;
			start ( );
		end
	
	always 
	begin
	   #500 scl = ~scl;
   end
   	
	always @ (posedge start_flag)
	begin
	   repeat (8)
	      begin
	         wait ( scl == 0 );
				#200;
				sda_out = data[7];
				#400;
				data = data << 1;
			end
			wait (~ scl);
			#200;
			sda_out = 1;
			#1600;
			stop ( );
	end 
	
	always @ ( posedge stop_flag)
	begin
//	   sda_out = 0;
//	   #500;
	   sda_out = 1;
	end   
	
	task start;   
	begin
		wait (scl == 0);
		#200;
		sda_out = 1;
		wait ( scl == 1 );
		#200;
		sda_out = 0;
		start_flag = 1;
	end
	endtask
		
	task stop;
	begin
		wait ( scl == 0 );
		#200;
		sda_out = 0;
		wait ( scl ==1 );
		#200;
		sda_out = 1;
		stop_flag = 1;
		end
	endtask
		
endmodule

2_Protocal_tb/6.i2c_csdn/i2c_csdn_tb.vcd
$date
	Thu Jul 15 17:09:04 2021
$end
$version
	Icarus Verilog
$end
$timescale
	1ps
$end
$scope module test $end
$var wire 1 ! sda $end
$var wire 1 " sda_in $end
$var reg 8 # data [7:0] $end
$var reg 1 $ scl $end
$var reg 1 % sda_out $end
$var reg 1 & start_flag $end
$var reg 1 ' stop_flag $end
$scope module testmine $end
$var wire 1 $ SCL $end
$var wire 1 ! SDA $end
$var wire 1 ( start $end
$var wire 1 ) stop $end
$var wire 1 * bit_ack $end
$var reg 1 + ack_assert $end
$var reg 1 , addr_match $end
$var reg 4 - bitcont [3:0] $end
$var reg 1 . op_read $end
$var reg 1 / sda1 $end
$var reg 1 0 sda11 $end
$var reg 1 1 sda2 $end
$var reg 1 2 sdar $end
$upscope $end
$scope task start $end
$upscope $end
$scope task stop $end
$upscope $end
$upscope $end
$enddefinitions $end
#0
$dumpvars
x2
x1
x0
x/
x.
bx -
x,
0+
x*
x)
x(
x'
0&
0%
0$
b100111 #
0"
0!
$end
#360000
1"
1!
1%
#500000
1/
12
1$
#700000
0"
0!
1&
0%
#1000000
0*
0.
1,
b110 -
1(
0)
10
01
0$
#1500000
02
0/
1$
#2000000
0(
00
0$
#2500000
b101 -
1$
#3000000
0$
#3500000
b100 -
1$
#4000000
0,
0$
#4500000
b11 -
1$
#5000000
0$
#5500000
b10 -
1$
#6000000
0$
#6500000
b1 -
1$
#7000000
0$
#7500000
b0 -
1$
#8000000
0$
#8500000
1*
b1111 -
1$
#9000000
0$
#9500000
0*
b110 -
1$
#10000000
0$
#10500000
b101 -
1$
#11000000
0$
#11500000
b100 -
1$
#12000000
0$
#12500000
b11 -
1$
#13000000
0$
#13500000
b10 -
1$
#14000000
0$
#14500000
b1 -
1$
#15000000
0$
#15500000
b0 -
1$
#16000000
0$
#16500000
1*
b1111 -
1$
#17000000
0$
#17500000
0*
b110 -
1$
#18000000
0$
#18500000
b101 -
1$
#19000000
0$
#19500000
b100 -
1$
#20000000
0$
#20500000
b11 -
1$
#21000000
0$
#21500000
b10 -
1$
#22000000
0$
#22500000
b1 -
1$
#23000000
0$
#23500000
b0 -
1$
#24000000
0$
#24500000
1*
b1111 -
1$
#25000000
0$
#25500000
0*
b110 -
1$
#26000000
0$
#26500000
b101 -
1$
#27000000
0$
#27500000
b100 -
1$
#28000000
0$
#28500000
b11 -
1$
#29000000
0$
#29500000
b10 -
1$
#30000000
0$
#30500000
b1 -
1$
#31000000
0$
#31500000
b0 -
1$
#32000000
0$
#32500000
1*
b1111 -
1$
#33000000
0$
#33500000
0*
b110 -
1$
#34000000
0$
#34500000
b101 -
1$
#35000000
0$
#35500000
b100 -
1$
#36000000
0$
#36500000
b11 -
1$
#37000000
0$
#37500000
b10 -
1$
#38000000
0$
#38500000
b1 -
1$
#39000000
0$
#39500000
b0 -
1$
#40000000
0$
#40500000
1*
b1111 -
1$
#41000000
0$
#41500000
0*
b110 -
1$
#42000000
0$
#42500000
b101 -
1$
#43000000
0$
#43500000
b100 -
1$
#44000000
0$
#44500000
b11 -
1$
#45000000
0$
#45500000
b10 -
1$
#46000000
0$
#46500000
b1 -
1$
#47000000
0$
#47500000
b0 -
1$
#48000000
0$
#48500000
1*
b1111 -
1$
#49000000
0$
#49500000
0*
b110 -
1$
#50000000
0$
#50500000
b101 -
1$
#51000000
0$
#51500000
b100 -
1$
#52000000
0$
#52500000
b11 -
1$
#53000000
0$
#53500000
b10 -
1$
#54000000
0$
#54500000
b1 -
1$
#55000000
0$
#55500000
b0 -
1$
#56000000
0$
#56500000
1*
b1111 -
1$
#57000000
0$
#57500000
0*
b110 -
1$
#58000000
0$
#58500000
b101 -
1$
#59000000
0$
#59500000
b100 -
1$
#60000000
0$
#60500000
b11 -
1$
#61000000
0$
#61500000
b10 -
1$
#62000000
0$
#62500000
b1 -
1$
#63000000
0$
#63500000
b0 -
1$
#64000000
0$
#64500000
1*
b1111 -
1$
#65000000
0$
#65500000
0*
b110 -
1$
#66000000
0$
#66500000
b101 -
1$
#67000000
0$
#67500000
b100 -
1$
#68000000
0$
#68500000
b11 -
1$
#69000000
0$
#69500000
b10 -
1$
#70000000
0$
#70500000
b1 -
1$
#71000000
0$
#71500000
b0 -
1$
#72000000
0$
#72500000
1*
b1111 -
1$
#73000000
0$
#73500000
0*
b110 -
1$
#74000000
0$
#74500000
b101 -
1$
#75000000
0$
#75500000
b100 -
1$
#76000000
0$
#76500000
b11 -
1$
#77000000
0$
#77500000
b10 -
1$
#78000000
0$
#78500000
b1 -
1$
#79000000
0$
#79500000
b0 -
1$
#80000000
0$
#80500000
1*
b1111 -
1$
#81000000
0$
#81500000
0*
b110 -
1$
#82000000
0$
#82500000
b101 -
1$
#83000000
0$
#83500000
b100 -
1$
#84000000
0$
#84500000
b11 -
1$
#85000000
0$
#85500000
b10 -
1$
#86000000
0$
#86500000
b1 -
1$
#87000000
0$
#87500000
b0 -
1$
#88000000
0$
#88500000
1*
b1111 -
1$
#89000000
0$
#89500000
0*
b110 -
1$
#90000000
0$
#90500000
b101 -
1$
#91000000
0$
#91500000
b100 -
1$
#92000000
0$
#92500000
b11 -
1$
#93000000
0$
#93500000
b10 -
1$
#94000000
0$
#94500000
b1 -
1$
#95000000
0$
#95500000
b0 -
1$
#96000000
0$
#96500000
1*
b1111 -
1$
#97000000
0$
#97500000
0*
b110 -
1$
#98000000
0$
#98500000
b101 -
1$
#99000000
0$
#99500000
b100 -
1$
#100000000
0$
